rakel/__init__.py
rakel/bridge/__init__.py
rakel/bridge/core-bridge.ts
rakel/bridge/generics.ts
rakel/bridge/index.ts
rakel/bridge/media-magic.ts
rakel/bridge/storage/MongoStorage.ts
rakel/bridge/storage/PostgresStorage.ts
rakel/bridge/storage/RedisStorage.ts
rakel/bridge/storage/StorageProvider.ts
rakel/bridge/storage/__init__.py
rakel/bridge/storage/index.ts
rakel/client/__init__.py
rakel/client/client.py
rakel/flow/__init__.py
rakel/flow/flow_manager.py
rakel/flow/mochi_flow.py
rakel_api-1.0.4.dist-info/METADATA
rakel_api-1.0.4.dist-info/WHEEL
rakel_api-1.0.4.dist-info/top_level.txt
rakel_api-1.0.4.dist-info/RECORD
