Metadata-Version: 2.4
Name: rakel-api
Version: 1.0.4
Summary: A WhatsApp Web API library infinitely superior for Python developers.
Author-email: Edward <edward@rakel.api.br>
Project-URL: Homepage, https://rakel.api.br
Project-URL: Bug Tracker, https://github.com/rakel-api/rakel/issues
Classifier: Programming Language :: Python :: 3
Classifier: License :: OSI Approved :: MIT License
Classifier: Operating System :: OS Independent
Requires-Python: >=3.8
Requires-Dist: loguru
